fastcdm/__init__.py
fastcdm/box.py
fastcdm/clean.py
fastcdm/colorize.py
fastcdm/core.py
fastcdm/latex_processor.py
fastcdm/matcher.py
fastcdm/tokenize.py
fastcdm/render/render_worker.py
fastcdm/render/templates/formula.html
fastcdm/render/templates/lib/auto-render.min.js
fastcdm/render/templates/lib/katex.min.css
fastcdm/render/templates/lib/katex.min.js
fastcdm/render/templates/lib/katex_fonts/KaTeX_AMS-Regular.ttf
fastcdm/render/templates/lib/katex_fonts/KaTeX_AMS-Regular.woff
fastcdm/render/templates/lib/katex_fonts/KaTeX_AMS-Regular.woff2
fastcdm/render/templates/lib/katex_fonts/KaTeX_Caligraphic-Bold.ttf
fastcdm/render/templates/lib/katex_fonts/KaTeX_Caligraphic-Bold.woff
fastcdm/render/templates/lib/katex_fonts/KaTeX_Caligraphic-Bold.woff2
fastcdm/render/templates/lib/katex_fonts/KaTeX_Caligraphic-Regular.ttf
fastcdm/render/templates/lib/katex_fonts/KaTeX_Caligraphic-Regular.woff
fastcdm/render/templates/lib/katex_fonts/KaTeX_Caligraphic-Regular.woff2
fastcdm/render/templates/lib/katex_fonts/KaTeX_Fraktur-Bold.ttf
fastcdm/render/templates/lib/katex_fonts/KaTeX_Fraktur-Bold.woff
fastcdm/render/templates/lib/katex_fonts/KaTeX_Fraktur-Bold.woff2
fastcdm/render/templates/lib/katex_fonts/KaTeX_Fraktur-Regular.ttf
fastcdm/render/templates/lib/katex_fonts/KaTeX_Fraktur-Regular.woff
fastcdm/render/templates/lib/katex_fonts/KaTeX_Fraktur-Regular.woff2
fastcdm/render/templates/lib/katex_fonts/KaTeX_Main-Bold.ttf
fastcdm/render/templates/lib/katex_fonts/KaTeX_Main-Bold.woff
fastcdm/render/templates/lib/katex_fonts/KaTeX_Main-Bold.woff2
fastcdm/render/templates/lib/katex_fonts/KaTeX_Main-BoldItalic.ttf
fastcdm/render/templates/lib/katex_fonts/KaTeX_Main-BoldItalic.woff
fastcdm/render/templates/lib/katex_fonts/KaTeX_Main-BoldItalic.woff2
fastcdm/render/templates/lib/katex_fonts/KaTeX_Main-Italic.ttf
fastcdm/render/templates/lib/katex_fonts/KaTeX_Main-Italic.woff
fastcdm/render/templates/lib/katex_fonts/KaTeX_Main-Italic.woff2
fastcdm-0.1.1.dist-info/LICENSE
fastcdm-0.1.1.dist-info/METADATA
fastcdm-0.1.1.dist-info/WHEEL
fastcdm-0.1.1.dist-info/top_level.txt
fastcdm-0.1.1.dist-info/RECORD
