Metadata-Version: 2.1
Name: fastcdm
Version: 0.1.1
Summary: Fast CDM utilities for LaTeX tokenization, rendering, and matching
Author: KevinQiu
License: Apache License
Classifier: License :: OSI Approved :: Apache Software License
Classifier: Programming Language :: Python :: 3
Classifier: Programming Language :: Python :: 3 :: Only
Classifier: Programming Language :: Python :: 3.8
Requires-Python: >=3.8
License-File: LICENSE
Requires-Dist: numpy >=1.20
Requires-Dist: opencv-python >=4.5
Requires-Dist: selenium >=4
Requires-Dist: webdriver-manager >=4
Requires-Dist: scikit-image
Requires-Dist: gradio
Provides-Extra: dev
Requires-Dist: pytest >=7 ; extra == 'dev'
Requires-Dist: black >=23 ; extra == 'dev'
Requires-Dist: ruff >=0.1 ; extra == 'dev'
Requires-Dist: mypy >=1.5 ; extra == 'dev'
Requires-Dist: twine ; extra == 'dev'
